{
    "matches": {
        "-30": [
            {
                "text": "M1528",
                "pixel_point": [
                    696.8794268152702,
                    1051.0791562071727
                ],
                "match_type": "inside"
            },
            {
                "text": "5%",
                "pixel_point": [
                    717.9201869045481,
                    796.8363754450179
                ],
                "match_type": "nearby",
                "distance": 37.043653320425534
            },
            {
                "text": "通道",
                "pixel_point": [
                    564.9226638212641,
                    878.8847513975561
                ],
                "match_type": "inside"
            }
        ],
        "-17": [
            {
                "text": "大厅",
                "pixel_point": [
                    1583.2189683463773,
                    2675.690434307015
                ],
                "match_type": "inside"
            },
            {
                "text": "学生活动室",
                "pixel_point": [
                    1905.1192850772927,
                    2771.5786253574756
                ],
                "match_type": "nearby",
                "distance": 25.89711139938096
            },
            {
                "text": "空调机房",
                "pixel_point": [
                    805.2825255221829,
                    2288.882374995171
                ],
                "match_type": "inside"
            },
            {
                "text": "电梯厅",
                "pixel_point": [
                    948.899889238186,
                    2185.0436897638215
                ],
                "match_type": "inside"
            },
            {
                "text": "货梯",
                "pixel_point": [
                    943.5887524123389,
                    2264.754192201486
                ],
                "match_type": "inside"
            },
            {
                "text": "无障碍电梯",
                "pixel_point": [
                    986.1684343960326,
                    2259.4496618369176
                ],
                "match_type": "inside"
            },
            {
                "text": "电梯厅",
                "pixel_point": [
                    2412.807338872302,
                    2528.6191355497617
                ],
                "match_type": "inside"
            },
            {
                "text": "强电间",
                "pixel_point": [
                    2580.7217335175815,
                    2727.9977097769934
                ],
                "match_type": "nearby",
                "distance": 26.826601637675314
            },
            {
                "text": "E1c-F1-10",
                "pixel_point": [
                    816.6458918164756,
                    2304.0701476710365
                ],
                "match_type": "inside"
            },
            {
                "text": "E1a-F1-02",
                "pixel_point": [
                    1910.4349998893038,
                    2789.1809135422523
                ],
                "match_type": "nearby",
                "distance": 25.857416957361608
            },
            {
                "text": "E1d-F1-01",
                "pixel_point": [
                    2401.6375316772396,
                    2545.209019564146
                ],
                "match_type": "inside"
            },
            {
                "text": "E1a-F1-01",
                "pixel_point": [
                    1058.4534053826621,
                    2728.7487228659816
                ],
                "match_type": "inside"
            },
            {
                "text": "报告厅（363人）",
                "pixel_point": [
                    1036.975994041909,
                    2707.535031792911
                ],
                "match_type": "inside"
            }
        ],
        "-29": [
            {
                "text": "女卫生间",
                "pixel_point": [
                    2333.4360829688535,
                    2773.3292375705773
                ],
                "match_type": "inside"
            }
        ],
        "-66": [
            {
                "text": "男卫生间",
                "pixel_point": [
                    2318.7508293770725,
                    2883.509588951004
                ],
                "match_type": "inside"
            }
        ],
        "-42": [
            {
                "text": "女卫生间",
                "pixel_point": [
                    1787.9406834737806,
                    170.17587182282568
                ],
                "match_type": "inside"
            },
            {
                "text": "微型教室",
                "pixel_point": [
                    2031.1935977125906,
                    399.4616969760882
                ],
                "match_type": "inside"
            },
            {
                "text": "微型教室",
                "pixel_point": [
                    1947.2645233954538,
                    411.4798307529368
                ],
                "match_type": "inside"
            },
            {
                "text": "微型教室",
                "pixel_point": [
                    1868.6516149156253,
                    422.57879625255964
                ],
                "match_type": "inside"
            },
            {
                "text": "微型教室",
                "pixel_point": [
                    1712.332308865268,
                    445.0501506617952
                ],
                "match_type": "inside"
            },
            {
                "text": "微型教室",
                "pixel_point": [
                    1633.5575646488353,
                    457.10141402101954
                ],
                "match_type": "inside"
            },
            {
                "text": "微型教室",
                "pixel_point": [
                    1555.2034072530378,
                    465.0587517560548
                ],
                "match_type": "inside"
            },
            {
                "text": "微型教室",
                "pixel_point": [
                    1477.621385940436,
                    476.67550808172246
                ],
                "match_type": "inside"
            },
            {
                "text": "微型教室",
                "pixel_point": [
                    1397.7362436850265,
                    486.8684374098266
                ],
                "match_type": "inside"
            },
            {
                "text": "微型教室",
                "pixel_point": [
                    1317.8571387401082,
                    498.413420248015
                ],
                "match_type": "inside"
            },
            {
                "text": "微型教室",
                "pixel_point": [
                    1241.5969424286886,
                    508.66336314552746
                ],
                "match_type": "inside"
            },
            {
                "text": "微型教室",
                "pixel_point": [
                    1162.445249151424,
                    517.9514043327194
                ],
                "match_type": "inside"
            },
            {
                "text": "微型教室",
                "pixel_point": [
                    1084.8807697675782,
                    531.2154801520319
                ],
                "match_type": "inside"
            },
            {
                "text": "微型教室",
                "pixel_point": [
                    1006.938953042061,
                    540.6723815481514
                ],
                "match_type": "inside"
            },
            {
                "text": "微型教室",
                "pixel_point": [
                    926.825883761993,
                    550.2202314087426
                ],
                "match_type": "inside"
            },
            {
                "text": "空调机房",
                "pixel_point": [
                    1790.7555038457185,
                    434.9712392806123
                ],
                "match_type": "inside"
            },
            {
                "text": "丙类储藏",
                "pixel_point": [
                    842.6411496609686,
                    528.4895649723458
                ],
                "match_type": "inside"
            },
            {
                "text": "开水间",
                "pixel_point": [
                    777.1984108181006,
                    530.6621382629041
                ],
                "match_type": "inside"
            },
            {
                "text": "空调机房",
                "pixel_point": [
                    713.3584603900265,
                    602.800687847724
                ],
                "match_type": "nearby",
                "distance": 16.31294907950707
            },
            {
                "text": "强电间",
                "pixel_point": [
                    670.6163130656809,
                    550.8018948407193
                ],
                "match_type": "inside"
            },
            {
                "text": "E2-F1-02",
                "pixel_point": [
                    720.9569951837154,
                    618.543685974124
                ],
                "match_type": "nearby",
                "distance": 12.280465067765036
            },
            {
                "text": "E2-F1-03",
                "pixel_point": [
                    850.498465725562,
                    541.7651718796706
                ],
                "match_type": "inside"
            },
            {
                "text": "E2-F1-04",
                "pixel_point": [
                    933.65731159809,
                    566.0557970927971
                ],
                "match_type": "inside"
            },
            {
                "text": "E2-F1-05",
                "pixel_point": [
                    1014.568806941475,
                    555.8728771334604
                ],
                "match_type": "nearby",
                "distance": 2.655308881797812
            },
            {
                "text": "E2-F1-06",
                "pixel_point": [
                    1092.4044120730714,
                    544.6340460974116
                ],
                "match_type": "nearby",
                "distance": 2.630241157467803
            },
            {
                "text": "E2-F1-07",
                "pixel_point": [
                    1170.766295968111,
                    533.1919804794275
                ],
                "match_type": "nearby",
                "distance": 1.7268584985318656
            },
            {
                "text": "E2-F1-08",
                "pixel_point": [
                    1248.6445300703886,
                    524.4173713463579
                ],
                "match_type": "nearby",
                "distance": 2.497511431884189
            },
            {
                "text": "E2-F1-09",
                "pixel_point": [
                    1324.1025620992248,
                    513.6351270483856
                ],
                "match_type": "nearby",
                "distance": 3.128122191249227
            },
            {
                "text": "E2-F1-10",
                "pixel_point": [
                    1404.0089849481737,
                    501.9060516653285
                ],
                "match_type": "inside"
            },
            {
                "text": "E2-F1-11",
                "pixel_point": [
                    1485.9461060397036,
                    491.13336177748624
                ],
                "match_type": "nearby",
                "distance": 1.5577481629117136
            },
            {
                "text": "E2-F1-12",
                "pixel_point": [
                    1562.9456320962188,
                    480.9444485725335
                ],
                "match_type": "nearby",
                "distance": 2.7638383691208026
            },
            {
                "text": "E2-F1-13",
                "pixel_point": [
                    1642.1869242606638,
                    470.90915747740246
                ],
                "match_type": "inside"
            },
            {
                "text": "E2-F1-15",
                "pixel_point": [
                    1800.04472045504,
                    449.6198966250231
                ],
                "match_type": "inside"
            },
            {
                "text": "E2-F1-17",
                "pixel_point": [
                    1956.3472432161795,
                    426.20349762092064
                ],
                "match_type": "inside"
            },
            {
                "text": "E2-F1-18",
                "pixel_point": [
                    2036.6419849252418,
                    415.0162336434546
                ],
                "match_type": "nearby",
                "distance": 1.3413717286543438
            },
            {
                "text": "男卫生间",
                "pixel_point": [
                    1970.9175774917062,
                    149.3873624060493
                ],
                "match_type": "inside"
            }
        ],
        "-16": [
            {
                "text": "客梯",
                "pixel_point": [
                    597.8129981943528,
                    553.449086347523
                ],
                "match_type": "inside"
            },
            {
                "text": "客梯",
                "pixel_point": [
                    606.8869894511405,
                    619.7771798756726
                ],
                "match_type": "inside"
            },
            {
                "text": "电梯厅",
                "pixel_point": [
                    532.9190257748025,
                    591.40612386866
                ],
                "match_type": "inside"
            },
            {
                "text": "门厅",
                "pixel_point": [
                    369.6186111675427,
                    574.385442992309
                ],
                "match_type": "inside"
            },
            {
                "text": "E2-F1-01",
                "pixel_point": [
                    363.42781992969856,
                    594.4720300281456
                ],
                "match_type": "inside"
            }
        ],
        "-59": [
            {
                "text": "通  廊",
                "pixel_point": [
                    1177.1019279368682,
                    346.4491906982412
                ],
                "match_type": "inside"
            }
        ],
        "-37": [
            {
                "text": "走道",
                "pixel_point": [
                    670.0113535671967,
                    1341.6740412116812
                ],
                "match_type": "nearby",
                "distance": 2.798425263375991
            },
            {
                "text": "教学实验室",
                "pixel_point": [
                    439.2174680971646,
                    1338.0250321987924
                ],
                "match_type": "inside"
            },
            {
                "text": "E1c-F1-02",
                "pixel_point": [
                    451.87730937025134,
                    1354.1949349700296
                ],
                "match_type": "inside"
            }
        ],
        "-39": [
            {
                "text": "教学实验室",
                "pixel_point": [
                    406.6937249297192,
                    1186.956610317995
                ],
                "match_type": "inside"
            },
            {
                "text": "E1c-F1-01",
                "pixel_point": [
                    418.7698758205358,
                    1203.233219854839
                ],
                "match_type": "inside"
            }
        ],
        "-54": [
            {
                "text": "教学实验室",
                "pixel_point": [
                    472.4781857674774,
                    1493.4710446068773
                ],
                "match_type": "inside"
            },
            {
                "text": "E1c-F1-03",
                "pixel_point": [
                    484.19851817536625,
                    1511.4248197803558
                ],
                "match_type": "inside"
            }
        ],
        "-50": [
            {
                "text": "教学实验室",
                "pixel_point": [
                    505.5062211734336,
                    1651.7916626300837
                ],
                "match_type": "inside"
            },
            {
                "text": "E1c-F1-04",
                "pixel_point": [
                    516.6022526367963,
                    1668.5971843623086
                ],
                "match_type": "inside"
            }
        ],
        "-36": [
            {
                "text": "教学实验室",
                "pixel_point": [
                    537.8529470895108,
                    1805.9891552718425
                ],
                "match_type": "inside"
            },
            {
                "text": "E1c-F1-05",
                "pixel_point": [
                    550.7823892001718,
                    1822.4463224090584
                ],
                "match_type": "inside"
            }
        ],
        "-40": [
            {
                "text": "教学实验室",
                "pixel_point": [
                    569.6683720586891,
                    1956.4913716842711
                ],
                "match_type": "inside"
            },
            {
                "text": "女卫生间",
                "pixel_point": [
                    532.5483428499293,
                    2076.5617227848697
                ],
                "match_type": "inside"
            },
            {
                "text": "E1c-F1-06",
                "pixel_point": [
                    584.2718101711206,
                    1972.3401150107682
                ],
                "match_type": "inside"
            }
        ],
        "-38": [
            {
                "text": "教学实验室",
                "pixel_point": [
                    753.5501938726107,
                    1266.1111007847119
                ],
                "match_type": "inside"
            },
            {
                "text": "E1c-F1-07",
                "pixel_point": [
                    765.1044077860402,
                    1281.7609054859201
                ],
                "match_type": "inside"
            }
        ],
        "-44": [
            {
                "text": "教学实验室",
                "pixel_point": [
                    821.342045622081,
                    1575.9674604116758
                ],
                "match_type": "inside"
            },
            {
                "text": "E1c-F1-08",
                "pixel_point": [
                    832.726779409948,
                    1591.9024180765966
                ],
                "match_type": "inside"
            }
        ],
        "-57": [
            {
                "text": "男卫生间",
                "pixel_point": [
                    551.6281584566716,
                    2161.1327075943304
                ],
                "match_type": "nearby",
                "distance": 4.866796797147692
            }
        ],
        "-51": [
            {
                "text": "男卫生间",
                "pixel_point": [
                    1436.5712246674461,
                    1863.3430638169848
                ],
                "match_type": "nearby",
                "distance": 8.699838912952483
            },
            {
                "text": "办公室",
                "pixel_point": [
                    1502.678665794641,
                    1721.9784949135253
                ],
                "match_type": "inside"
            },
            {
                "text": "办公室",
                "pixel_point": [
                    1423.9463096639508,
                    1712.5707022922631
                ],
                "match_type": "inside"
            },
            {
                "text": "空调机房",
                "pixel_point": [
                    1307.3162145249362,
                    1706.0081573807008
                ],
                "match_type": "inside"
            }
        ],
        "-81": [
            {
                "text": "淋浴",
                "pixel_point": [
                    1511.6810939272116,
                    1971.9610321626212
                ],
                "match_type": "nearby",
                "distance": 16.284110425054127
            }
        ],
        "-32": [
            {
                "text": "理论与计算研究室",
                "pixel_point": [
                    1378.133276568454,
                    2260.2439031163904
                ],
                "match_type": "inside"
            },
            {
                "text": "E1b-F1-08",
                "pixel_point": [
                    1396.905391814974,
                    2279.2781760114863
                ],
                "match_type": "inside"
            }
        ],
        "-86": [
            {
                "text": "理论与计算研究室",
                "pixel_point": [
                    1529.708866553814,
                    2260.622794403049
                ],
                "match_type": "nearby",
                "distance": 0.29203704194713864
            },
            {
                "text": "E1b-F1-09",
                "pixel_point": [
                    1553.8363044532366,
                    2279.288320946811
                ],
                "match_type": "inside"
            }
        ],
        "-27": [
            {
                "text": "理论与计算研究室",
                "pixel_point": [
                    1690.2857707017386,
                    2260.622794403049
                ],
                "match_type": "inside"
            },
            {
                "text": "E1b-F1-10",
                "pixel_point": [
                    1714.4311554420983,
                    2279.4117612023106
                ],
                "match_type": "inside"
            }
        ],
        "-24": [
            {
                "text": "理论与计算研究室",
                "pixel_point": [
                    1848.517058079114,
                    2260.622794403049
                ],
                "match_type": "inside"
            },
            {
                "text": "E1b-F1-11",
                "pixel_point": [
                    1873.8534988528454,
                    2281.4092243056284
                ],
                "match_type": "inside"
            }
        ],
        "-87": [
            {
                "text": "理论与计算研究室",
                "pixel_point": [
                    2006.9635468031365,
                    2260.622794403049
                ],
                "match_type": "inside"
            },
            {
                "text": "E1b-F1-12",
                "pixel_point": [
                    2026.3394040166086,
                    2279.6735904487236
                ],
                "match_type": "inside"
            }
        ],
        "-45": [
            {
                "text": "理论与计算研究室",
                "pixel_point": [
                    1580.1492673236926,
                    1884.953727829604
                ],
                "match_type": "inside"
            },
            {
                "text": "E1b-F1-04",
                "pixel_point": [
                    1602.3978038787657,
                    1902.4139427103169
                ],
                "match_type": "inside"
            }
        ],
        "-49": [
            {
                "text": "理论与计算研究室",
                "pixel_point": [
                    1733.6205314771748,
                    1904.1709371463783
                ],
                "match_type": "inside"
            },
            {
                "text": "E1b-F1-05",
                "pixel_point": [
                    1756.8504237649313,
                    1922.3241569838976
                ],
                "match_type": "inside"
            }
        ],
        "-46": [
            {
                "text": "理论与计算研究室",
                "pixel_point": [
                    1890.3872330612962,
                    1916.9352480005314
                ],
                "match_type": "inside"
            },
            {
                "text": "E1b-F1-06",
                "pixel_point": [
                    1916.0650675483453,
                    1937.0474872979828
                ],
                "match_type": "inside"
            }
        ],
        "-48": [
            {
                "text": "理论与计算研究室",
                "pixel_point": [
                    2049.7233029015642,
                    1934.6609861833815
                ],
                "match_type": "inside"
            },
            {
                "text": "E1b-F1-07",
                "pixel_point": [
                    2073.863432458333,
                    1953.8052514936744
                ],
                "match_type": "inside"
            }
        ],
        "-5": [
            {
                "text": "走道",
                "pixel_point": [
                    1625.487108368342,
                    2063.607603230529
                ],
                "match_type": "inside"
            },
            {
                "text": "开水间",
                "pixel_point": [
                    2214.1393233203935,
                    2045.484989009726
                ],
                "match_type": "nearby",
                "distance": 36.22552481339945
            },
            {
                "text": "电梯厅",
                "pixel_point": [
                    2154.103002032379,
                    2199.5818128082833
                ],
                "match_type": "inside"
            }
        ],
        "-53": [
            {
                "text": "阳台",
                "pixel_point": [
                    1841.0744882043232,
                    1777.0946538977971
                ],
                "match_type": "nearby",
                "distance": 1.2076257268006354
            }
        ],
        "-41": [
            {
                "text": "强电间",
                "pixel_point": [
                    2229.196164204102,
                    1967.5310535164087
                ],
                "match_type": "nearby",
                "distance": 41.84302063131787
            },
            {
                "text": "储藏室",
                "pixel_point": [
                    2219.4610881824183,
                    2016.4705296195664
                ],
                "match_type": "nearby",
                "distance": 47.69630731187992
            }
        ],
        "-25": [
            {
                "text": "空调机房",
                "pixel_point": [
                    2658.2849403579457,
                    2515.0643933227
                ],
                "match_type": "inside"
            },
            {
                "text": "E1d-F1-02",
                "pixel_point": [
                    2654.9430038843684,
                    2532.340923658725
                ],
                "match_type": "inside"
            }
        ],
        "-26": [
            {
                "text": "测试实验研究室（干）",
                "pixel_point": [
                    2845.1830787175636,
                    2532.783821850519
                ],
                "match_type": "inside"
            },
            {
                "text": "E1d-F1-03",
                "pixel_point": [
                    2863.360726866214,
                    2552.7675511319203
                ],
                "match_type": "inside"
            }
        ],
        "-8": [
            {
                "text": "测试实验研究室（干）",
                "pixel_point": [
                    3139.6540433645205,
                    2561.0344896759457
                ],
                "match_type": "inside"
            },
            {
                "text": "E1d-F1-04",
                "pixel_point": [
                    3169.5448307132274,
                    2580.269738044095
                ],
                "match_type": "inside"
            }
        ],
        "-6": [
            {
                "text": "测试实验研究室（干）",
                "pixel_point": [
                    3460.499745979027,
                    2584.3847481130097
                ],
                "match_type": "inside"
            },
            {
                "text": "E1d-F1-05",
                "pixel_point": [
                    3485.8628755700192,
                    2605.201825962252
                ],
                "match_type": "inside"
            }
        ],
        "-47": [
            {
                "text": "测试实验研究室（干）",
                "pixel_point": [
                    3727.0544505218513,
                    2604.492371364488
                ],
                "match_type": "inside"
            },
            {
                "text": "E1d-F1-06",
                "pixel_point": [
                    3753.289678655085,
                    2623.9534321252227
                ],
                "match_type": "inside"
            }
        ],
        "-4": [
            {
                "text": "测试实验研究室（湿）",
                "pixel_point": [
                    3082.7179859142375,
                    2835.1577501030783
                ],
                "match_type": "inside"
            },
            {
                "text": "E1d-F1-13",
                "pixel_point": [
                    3104.3013979757866,
                    2859.221105330092
                ],
                "match_type": "inside"
            }
        ],
        "-20": [
            {
                "text": "测试实验研究室（湿）",
                "pixel_point": [
                    3520.7668632452383,
                    2885.4085799268455
                ],
                "match_type": "inside"
            },
            {
                "text": "E1d-F1-14",
                "pixel_point": [
                    3555.087374308882,
                    2907.9140704671777
                ],
                "match_type": "inside"
            }
        ],
        "-82": [
            {
                "text": "开水间",
                "pixel_point": [
                    2652.659645647753,
                    2795.062000092803
                ],
                "match_type": "nearby",
                "distance": 12.50166260366823
            }
        ],
        "-63": [
            {
                "text": "会议室",
                "pixel_point": [
                    2778.529300003529,
                    2755.7896653108055
                ],
                "match_type": "inside"
            },
            {
                "text": "E1d-F1-07",
                "pixel_point": [
                    2773.0240769623774,
                    2772.2138731928067
                ],
                "match_type": "inside"
            }
        ],
        "-84": [
            {
                "text": "办公室",
                "pixel_point": [
                    2555.4342839535775,
                    2880.839888036283
                ],
                "match_type": "inside"
            },
            {
                "text": "E1d-F1-08",
                "pixel_point": [
                    2546.06416127766,
                    2896.260257344409
                ],
                "match_type": "inside"
            }
        ],
        "-85": [
            {
                "text": "办公室",
                "pixel_point": [
                    2637.9546667327522,
                    2887.216545847409
                ],
                "match_type": "inside"
            },
            {
                "text": "E1d-F1-09",
                "pixel_point": [
                    2627.752023346064,
                    2903.2373609369474
                ],
                "match_type": "inside"
            }
        ],
        "-83": [
            {
                "text": "办公室",
                "pixel_point": [
                    2713.6509780748406,
                    2893.2967872868544
                ],
                "match_type": "inside"
            },
            {
                "text": "E1d-F1-10",
                "pixel_point": [
                    2703.455649543894,
                    2908.9002821322724
                ],
                "match_type": "inside"
            }
        ],
        "-80": [
            {
                "text": "办公室",
                "pixel_point": [
                    2794.8455307116824,
                    2900.6696797206046
                ],
                "match_type": "inside"
            },
            {
                "text": "E1d-F1-11",
                "pixel_point": [
                    2788.0157147374493,
                    2915.1681650330893
                ],
                "match_type": "inside"
            }
        ],
        "-79": [
            {
                "text": "办公室",
                "pixel_point": [
                    2875.4952247155293,
                    2906.803575303158
                ],
                "match_type": "inside"
            },
            {
                "text": "E1d-F1-12",
                "pixel_point": [
                    2870.038054835598,
                    2924.111634172747
                ],
                "match_type": "inside"
            }
        ],
        "-34": [
            {
                "text": "教学实验室",
                "pixel_point": [
                    881.6507077521517,
                    1877.6515725169672
                ],
                "match_type": "inside"
            },
            {
                "text": "E1c-F1-09",
                "pixel_point": [
                    892.8767300502006,
                    1893.1068567941825
                ],
                "match_type": "inside"
            }
        ],
        "-69": [
            {
                "text": "E2-F1-14",
                "pixel_point": [
                    1718.234971801977,
                    460.70613154886087
                ],
                "match_type": "nearby",
                "distance": 1.970079293254377
            }
        ],
        "-70": [
            {
                "text": "E2-F1-16",
                "pixel_point": [
                    1876.3242704598465,
                    438.23866150616414
                ],
                "match_type": "nearby",
                "distance": 2.7536322524245174
            }
        ]
    },
    "unmatched": [
        {
            "text": "排水暗沟",
            "pixel_point": [
                1512.5018956560339,
                168.56711121320677
            ],
            "best_candidate": "-59",
            "distance": 92.27669625723456
        },
        {
            "text": "室外庭院",
            "pixel_point": [
                1391.0213362763136,
                754.0566130122538
            ],
            "best_candidate": "-74",
            "distance": 121.55062846027074
        },
        {
            "text": "女卫生间",
            "pixel_point": [
                1413.0113920497133,
                1946.5257412768258
            ],
            "best_candidate": "-81",
            "distance": 57.09962408375137
        },
        {
            "text": "清洁间",
            "pixel_point": [
                2449.867652369552,
                2851.8187978735723
            ],
            "best_candidate": "-66",
            "distance": 58.877937105231375
        },
        {
            "text": "残卫",
            "pixel_point": [
                1363.1511553958062,
                1867.9001606425504
            ],
            "best_candidate": "-51",
            "distance": 63.2284893310536
        },
        {
            "text": "清洁间",
            "pixel_point": [
                1337.2073271813529,
                1947.514428241386
            ],
            "best_candidate": "-5",
            "distance": 59.4620907783881
        }
    ],
    "statistics": {
        "total_texts": 145,
        "matched_texts": 139,
        "unmatched_texts": 6,
        "match_rate": "95.86%",
        "rooms_with_matches": 47,
        "rooms_updated_in_osm": 47
    },
    "boundary_info": {
        "min_x": 58.00087258064059,
        "min_y": 122.9945734024509,
        "max_x": 3891.9979560437555,
        "max_y": 3267.978288816848,
        "min_x_padded": -57.01903992325285,
        "min_y_padded": 7.97466089855746,
        "max_x_padded": 4007.017868547649,
        "max_y_padded": 3382.9982013207414,
        "padding": 115.01991250389344,
        "padding_ratio": 0.03,
        "scale": 1.06
    }
}